play_sql/__init__.py
play_sql/providers.py
play_sql-0.0.3.dist-info/LICENSE
play_sql-0.0.3.dist-info/METADATA
play_sql-0.0.3.dist-info/WHEEL
play_sql-0.0.3.dist-info/entry_points.txt
play_sql-0.0.3.dist-info/top_level.txt
play_sql-0.0.3.dist-info/RECORD
